recursive_handlers/__init__.py
recursive_handlers-0.2.0.dist-info/METADATA
recursive_handlers-0.2.0.dist-info/WHEEL
recursive_handlers-0.2.0.dist-info/RECORD
