Metadata-Version: 2.3
Name: recursive-handlers
Version: 0.2.0
Summary: Add your description here
Project-URL: Documentation, https://github.com/Tomperez98/recursive-handlers#readme
Project-URL: Issues, https://github.com/Tomperez98/recursive-handlers/issues
Project-URL: Source, https://github.com/Tomperez98/recursive-handlers
Author-email: Tomperez98 <tomasperezalvarez@gmail.com>
Requires-Python: >=3.10
Requires-Dist: result>=0.16.1
